hindi_xlit/__init__.py
hindi_xlit/hindi_model.py
hindi_xlit/transliterator.py
hindi_xlit/models/hindi/hi_111_model.pth
hindi_xlit/models/hindi/hi_scripts.json
hindi_xlit/models/hindi/hi_words_a4b.json
hindi_xlit-1.0.1.dist-info/licenses/LICENSE
hindi_xlit-1.0.1.dist-info/METADATA
hindi_xlit-1.0.1.dist-info/WHEEL
hindi_xlit-1.0.1.dist-info/entry_points.txt
hindi_xlit-1.0.1.dist-info/top_level.txt
hindi_xlit-1.0.1.dist-info/RECORD
