Metadata-Version: 2.4
Name: hindi_xlit
Version: 1.0.1
Summary: A Hindi transliteration library based on AI4Bharat's IndicXlit
Author-email: Aman Ranjan Verma <aman.ranjanverma@gmail.com>
License: MIT License
Project-URL: Homepage, https://github.com/arverma/HindiXlit
Project-URL: Repository, https://github.com/arverma/HindiXlit.git
Classifier: Development Status :: 4 - Beta
Classifier: Intended Audience :: Developers
Classifier: License :: OSI Approved :: MIT License
Classifier: Operating System :: OS Independent
Classifier: Programming Language :: Python :: 3
Classifier: Programming Language :: Python :: 3.6
Classifier: Programming Language :: Python :: 3.7
Classifier: Programming Language :: Python :: 3.8
Classifier: Programming Language :: Python :: 3.9
Classifier: Programming Language :: Python :: 3.10
Classifier: Programming Language :: Python :: 3.11
Classifier: Topic :: Text Processing :: Linguistic
Classifier: Natural Language :: Hindi
Classifier: Natural Language :: English
Requires-Python: >=3.6
License-File: LICENSE
Requires-Dist: torch<3.0.0,>=2.0.0
Requires-Dist: numpy<2.3.0,>=2.0.0
Provides-Extra: dev
Requires-Dist: build>=0.10.0; extra == "dev"
Requires-Dist: twine>=4.0.0; extra == "dev"
Requires-Dist: black>=23.0.0; extra == "dev"
Requires-Dist: flake8>=6.0.0; extra == "dev"
Dynamic: license-file
